manydepth/__init__.py
manydepth/__main__.py
manydepth/evaluate_depth.py
manydepth/export_gt_depth.py
manydepth/kitti_utils.py
manydepth/layers.py
manydepth/options.py
manydepth/test_simple.py
manydepth/train.py
manydepth/trainer.py
manydepth/utils.py
manydepth/networks/__init__.py
manydepth/networks/depth_decoder.py
manydepth/networks/pose_cnn.py
manydepth/networks/pose_decoder.py
manydepth/networks/resnet_encoder.py
manydepth-1.0.0.dist-info/LICENSE
manydepth-1.0.0.dist-info/METADATA
manydepth-1.0.0.dist-info/WHEEL
manydepth-1.0.0.dist-info/top_level.txt
manydepth-1.0.0.dist-info/RECORD
