Metadata-Version: 2.1
Name: manydepth
Version: 1.0.0
Summary: [CVPR 2021] Self-supervised depth estimation from short sequences
Home-page: https://github.com/AdityaNG/monodepth2
License: LICENSE
Platform: UNKNOWN
Requires-Python: >=3.6
